dashvector/__init__.py
dashvector/common/__init__.py
dashvector/common/common_validator.py
dashvector/common/constants.py
dashvector/common/error.py
dashvector/common/handler.py
dashvector/common/logging.py
dashvector/common/status.py
dashvector/common/types.py
dashvector/common/vector_validator.py
dashvector/core/__init__.py
dashvector/core/client.py
dashvector/core/collection.py
dashvector/core/doc.py
dashvector/core/group.py
dashvector/core/handler/__init__.py
dashvector/core/handler/grpc_handler.py
dashvector/core/handler/http_handler.py
dashvector/core/index.py
dashvector/core/models/__init__.py
dashvector/core/models/collection_meta_status.py
dashvector/core/models/create_collection_request.py
dashvector/core/models/create_partition_request.py
dashvector/core/models/delete_collection_request.py
dashvector/core/models/delete_doc_request.py
dashvector/core/models/delete_partition_request.py
dashvector/core/models/describe_collection_request.py
dashvector/core/models/describe_partition_request.py
dashvector/core/models/fetch_doc_request.py
dashvector/core/models/get_version_request.py
dashvector/core/models/list_collections_request.py
dashvector/core/models/list_partitions_request.py
dashvector/core/models/partition_meta_status.py
dashvector/core/models/query_doc_group_by_request.py
dashvector/core/models/query_doc_request.py
dashvector/core/models/stats_collection_request.py
dashvector/core/models/stats_partition_request.py
dashvector/core/models/upsert_doc_request.py
dashvector/core/proto/__init__.py
dashvector/core/proto/dashvector_pb2.py
dashvector/core/proto/dashvector_pb2.pyi
dashvector/core/proto/dashvector_pb2_grpc.py
dashvector/util/__init__.py
dashvector/util/convertor.py
dashvector/util/validator.py
dashvector/version.py
dashvector-1.0.23.dist-info/LICENSE.txt
dashvector-1.0.23.dist-info/METADATA
dashvector-1.0.23.dist-info/WHEEL
dashvector-1.0.23.dist-info/RECORD
