Metadata-Version: 2.1
Name: dashvector
Version: 1.0.23
Summary: DashVector Client Python Sdk Library
Home-page: https://github.com/alibaba/proxima
License: Apache-2.0
Keywords: DashVector,vector,database,cloud
Author: Alibaba
Requires-Python: >=3.9,<4.0
Classifier: Development Status :: 5 - Production/Stable
Classifier: Intended Audience :: Developers
Classifier: License :: OSI Approved :: Apache Software License
Classifier: Programming Language :: Python
Classifier: Programming Language :: Python :: 3
Classifier: Programming Language :: Python :: 3.9
Classifier: Programming Language :: Python :: 3.10
Classifier: Programming Language :: Python :: 3.11
Classifier: Programming Language :: Python :: 3.12
Classifier: Topic :: Database
Classifier: Topic :: Software Development
Classifier: Topic :: Software Development :: Libraries
Classifier: Topic :: Software Development :: Libraries :: Application Frameworks
Classifier: Topic :: Software Development :: Libraries :: Python Modules
Requires-Dist: aiohttp (>=3.1.0,<4.0.0)
Requires-Dist: certifi (>=2023.7.22,<2024.0.0)
Requires-Dist: grpcio (>=1.44.0) ; python_version >= "3.8" and python_version < "3.11"
Requires-Dist: grpcio (>=1.59.0) ; python_version >= "3.11" and python_version < "4.0"
Requires-Dist: importlib_metadata
Requires-Dist: numpy
Requires-Dist: protobuf (>=5.29,<6.0)
Project-URL: Documentation, https://help.aliyun.com/document_detail/2510225.html
